CHANGELOG
LICENSE
MANIFEST.in
README.txt
setup.py
test_convert_unittest.py
test_pycmd.py
tox.ini
pycmd/__init__.py
pycmd/pycleanup.py
pycmd/pyconvert_unittest.py
pycmd/pycountloc.py
pycmd/pylookup.py
pycmd/pysvnwcrevert.py
pycmd/pywhich.py
pycmd.egg-info/PKG-INFO
pycmd.egg-info/SOURCES.txt
pycmd.egg-info/dependency_links.txt
pycmd.egg-info/entry_points.txt
pycmd.egg-info/not-zip-safe
pycmd.egg-info/requires.txt
pycmd.egg-info/top_level.txt